setup_cfg_fmt.py
setup_cfg_fmt-3.2.0.dist-info/LICENSE
setup_cfg_fmt-3.2.0.dist-info/METADATA
setup_cfg_fmt-3.2.0.dist-info/WHEEL
setup_cfg_fmt-3.2.0.dist-info/entry_points.txt
setup_cfg_fmt-3.2.0.dist-info/top_level.txt
setup_cfg_fmt-3.2.0.dist-info/RECORD
