Metadata-Version: 2.1
Name: setup_cfg_fmt
Version: 3.2.0
Summary: apply a consistent format to `setup.cfg` files
Home-page: https://github.com/asottile/setup-cfg-fmt
Author: Anthony Sottile
Author-email: asottile@umich.edu
License: MIT
Classifier: Programming Language :: Python :: 3
Classifier: Programming Language :: Python :: 3 :: Only
Classifier: Programming Language :: Python :: Implementation :: CPython
Classifier: Programming Language :: Python :: Implementation :: PyPy
Requires-Python: >=3.10
License-File: LICENSE
Requires-Dist: identify[license]>=2.4.0
